ovos_tts_plugin_nos/__init__.py
ovos_tts_plugin_nos/cotovia_aarch64
ovos_tts_plugin_nos/cotovia_x86_64
ovos_tts_plugin_nos/version.py
ovos_tts_plugin_nos/vits_onnx.py
ovos_tts_plugin_nos-0.7.4.dist-info/licenses/LICENSE
ovos_tts_plugin_nos-0.7.4.dist-info/METADATA
ovos_tts_plugin_nos-0.7.4.dist-info/WHEEL
ovos_tts_plugin_nos-0.7.4.dist-info/entry_points.txt
ovos_tts_plugin_nos-0.7.4.dist-info/top_level.txt
ovos_tts_plugin_nos-0.7.4.dist-info/zip-safe
ovos_tts_plugin_nos-0.7.4.dist-info/RECORD
