Metadata-Version: 2.4
Name: ovos-tts-plugin-nos
Version: 0.7.4
Summary: A galician tts plugin for OVOS
Home-page: https://github.com/OpenVoiceOS/ovos-tts-plugin-nos
Author: JarbasAi
Author-email: jarbasai@mailfence.com
License: Apache-2.0
Keywords: mycroft ovos plugin tts
Classifier: Development Status :: 3 - Alpha
Classifier: Intended Audience :: Developers
Classifier: Topic :: Text Processing :: Linguistic
Classifier: License :: OSI Approved :: Apache Software License
Classifier: Programming Language :: Python :: 2
Classifier: Programming Language :: Python :: 2.7
Classifier: Programming Language :: Python :: 3
Classifier: Programming Language :: Python :: 3.0
Classifier: Programming Language :: Python :: 3.1
Classifier: Programming Language :: Python :: 3.2
Classifier: Programming Language :: Python :: 3.3
Classifier: Programming Language :: Python :: 3.4
Classifier: Programming Language :: Python :: 3.5
Classifier: Programming Language :: Python :: 3.6
License-File: LICENSE
Requires-Dist: numpy<2.0.0
Requires-Dist: scipy
Requires-Dist: onnxruntime<=1.20.1
Requires-Dist: ovos-plugin-manager<2.0.0,>=1.0.0
Dynamic: author
Dynamic: author-email
Dynamic: classifier
Dynamic: home-page
Dynamic: keywords
Dynamic: license
Dynamic: license-file
Dynamic: requires-dist
Dynamic: summary
